HISTORY.rst
LICENSE
MANIFEST.in
README.rst
dynamo.py
setup.py
dynamo.egg-info/PKG-INFO
dynamo.egg-info/SOURCES.txt
dynamo.egg-info/dependency_links.txt
dynamo.egg-info/requires.txt
dynamo.egg-info/top_level.txt