Metadata-Version: 1.1
Name: dynamo
Version: 0.1.1
Summary: Simple DynamoDB Interface.
Home-page: https://github.com/kennethreitz/dynamo
Author: Kenneth Reitz
Author-email: me@kennethreitz.com
License: Copyright (c) 2012 Kenneth Reitz.
